ml4t/data/AGENT.md
ml4t/data/__init__.py
ml4t/data/_version.py
ml4t/data/cli_interface.py
ml4t/data/data_manager.py
ml4t/data/provider_updater.py
ml4t/data/py.typed
ml4t/data/universe.py
ml4t/data/update_manager.py
ml4t/data/adjustments/__init__.py
ml4t/data/adjustments/core.py
ml4t/data/anomaly/AGENT.md
ml4t/data/anomaly/__init__.py
ml4t/data/anomaly/base.py
ml4t/data/anomaly/config.py
ml4t/data/anomaly/detectors.py
ml4t/data/anomaly/manager.py
ml4t/data/assets/AGENT.md
ml4t/data/assets/__init__.py
ml4t/data/assets/asset_class.py
ml4t/data/assets/contracts.py
ml4t/data/assets/schemas.py
ml4t/data/assets/validation.py
ml4t/data/calendar/__init__.py
ml4t/data/calendar/crypto.py
ml4t/data/cli/__init__.py
ml4t/data/cli/batch.py
ml4t/data/cli/config.py
ml4t/data/cli/core.py
ml4t/data/cli/cot.py
ml4t/data/cli/futures.py
ml4t/data/cli/utils.py
ml4t/data/config/__init__.py
ml4t/data/config/loader.py
ml4t/data/config/models.py
ml4t/data/config/validator.py
ml4t/data/core/AGENT.md
ml4t/data/core/__init__.py
ml4t/data/core/config.py
ml4t/data/core/exceptions.py
ml4t/data/core/models.py
ml4t/data/core/schemas.py
ml4t/data/cot/AGENT.md
ml4t/data/cot/__init__.py
ml4t/data/cot/fetcher.py
ml4t/data/cot/workflow.py
ml4t/data/crypto/__init__.py
ml4t/data/crypto/downloader.py
ml4t/data/etfs/__init__.py
ml4t/data/etfs/downloader.py
ml4t/data/export/__init__.py
ml4t/data/export/manager.py
ml4t/data/export/formats/__init__.py
ml4t/data/export/formats/base.py
ml4t/data/export/formats/csv.py
ml4t/data/export/formats/excel.py
ml4t/data/export/formats/json.py
ml4t/data/futures/AGENT.md
ml4t/data/futures/__init__.py
ml4t/data/futures/adjustment.py
ml4t/data/futures/book_downloader.py
ml4t/data/futures/config.py
ml4t/data/futures/continuous.py
ml4t/data/futures/databento_parser.py
ml4t/data/futures/definitions.py
ml4t/data/futures/downloader.py
ml4t/data/futures/parser.py
ml4t/data/futures/roll.py
ml4t/data/futures/schema.py
ml4t/data/macro/__init__.py
ml4t/data/macro/downloader.py
ml4t_data-0.1.0a6.dist-info/METADATA
ml4t_data-0.1.0a6.dist-info/WHEEL
ml4t_data-0.1.0a6.dist-info/entry_points.txt
ml4t_data-0.1.0a6.dist-info/licenses/LICENSE
ml4t_data-0.1.0a6.dist-info/RECORD
