Metadata-Version: 2.4
Name: ml4t-data
Version: 0.1.0a6
Summary: High-performance market data management library with unified multi-provider interface
Project-URL: Homepage, https://github.com/stefan-jansen/ml4t-data
Project-URL: Documentation, https://ml4t-data.readthedocs.io
Project-URL: Repository, https://github.com/stefan-jansen/ml4t-data
Project-URL: Issues, https://github.com/stefan-jansen/ml4t-data/issues
Project-URL: Changelog, https://github.com/stefan-jansen/ml4t-data/blob/main/CHANGELOG.md
Author-email: ML4T Team <info@ml4trading.io>
Maintainer-email: ML4T Contributors <dev@ml4trading.io>
License: MIT
License-File: LICENSE
Keywords: backtesting,binance,cryptocompare,databento,finance,market-data,oanda,parquet,polars,quantitative-finance,trading,yahoo-finance
Classifier: Development Status :: 3 - Alpha
Classifier: Intended Audience :: Developers
Classifier: Intended Audience :: Financial and Insurance Industry
Classifier: Intended Audience :: Science/Research
Classifier: License :: OSI Approved :: MIT License
Classifier: Operating System :: OS Independent
Classifier: Programming Language :: Python :: 3
Classifier: Programming Language :: Python :: 3.11
Classifier: Programming Language :: Python :: 3.12
Classifier: Programming Language :: Python :: 3.13
Classifier: Topic :: Office/Business :: Financial :: Investment
Classifier: Topic :: Scientific/Engineering :: Information Analysis
Classifier: Typing :: Typed
Requires-Python: >=3.11
Requires-Dist: aiofiles>=23.0.0
Requires-Dist: click>=8.0.0
Requires-Dist: filelock>=3.19.1
Requires-Dist: html5lib>=1.1
Requires-Dist: httpx>=0.25.0
Requires-Dist: lxml>=6.0.2
Requires-Dist: numpy>=1.24.0
Requires-Dist: pandas-market-calendars>=4.3.0
Requires-Dist: pandas>=2.0.0
Requires-Dist: platformdirs>=4.0.0
Requires-Dist: polars>=0.20.0
Requires-Dist: pyarrow>=14.0.0
Requires-Dist: pybreaker>=1.0.0
Requires-Dist: pydantic-settings>=2.0.0
Requires-Dist: python-dotenv>=1.0.0
Requires-Dist: pyyaml>=6.0
Requires-Dist: rich>=13.0.0
Requires-Dist: structlog>=23.0.0
Requires-Dist: tenacity>=8.0.0
Provides-Extra: all
Requires-Dist: cot-reports>=0.1.0; extra == 'all'
Requires-Dist: databento>=0.38.0; extra == 'all'
Requires-Dist: hypothesis>=6.80.0; extra == 'all'
Requires-Dist: ipdb>=0.13.0; extra == 'all'
Requires-Dist: ipython>=8.14.0; extra == 'all'
Requires-Dist: mkdocs-git-revision-date-localized-plugin>=1.2.0; extra == 'all'
Requires-Dist: mkdocs-material>=9.5.0; extra == 'all'
Requires-Dist: mkdocs>=1.6.0; extra == 'all'
Requires-Dist: mkdocstrings[python]>=0.24.0; extra == 'all'
Requires-Dist: mypy>=1.5.0; extra == 'all'
Requires-Dist: oandapyv20>=0.7.0; extra == 'all'
Requires-Dist: pre-commit>=3.3.0; extra == 'all'
Requires-Dist: pytest-asyncio>=0.21.0; extra == 'all'
Requires-Dist: pytest-cov>=4.1.0; extra == 'all'
Requires-Dist: pytest-timeout>=2.1.0; extra == 'all'
Requires-Dist: pytest-xdist>=3.3.0; extra == 'all'
Requires-Dist: pytest>=7.4.0; extra == 'all'
Requires-Dist: ruff>=0.1.0; extra == 'all'
Requires-Dist: xlsxwriter>=3.1.0; extra == 'all'
Requires-Dist: yfinance>=0.2.0; extra == 'all'
Provides-Extra: all-providers
Requires-Dist: cot-reports>=0.1.0; extra == 'all-providers'
Requires-Dist: databento>=0.38.0; extra == 'all-providers'
Requires-Dist: oandapyv20>=0.7.0; extra == 'all-providers'
Requires-Dist: yfinance>=0.2.0; extra == 'all-providers'
Provides-Extra: cot
Requires-Dist: cot-reports>=0.1.0; extra == 'cot'
Provides-Extra: databento
Requires-Dist: databento>=0.38.0; extra == 'databento'
Provides-Extra: dev
Requires-Dist: hypothesis>=6.80.0; extra == 'dev'
Requires-Dist: ipdb>=0.13.0; extra == 'dev'
Requires-Dist: ipython>=8.14.0; extra == 'dev'
Requires-Dist: mypy>=1.5.0; extra == 'dev'
Requires-Dist: pre-commit>=3.3.0; extra == 'dev'
Requires-Dist: pytest-asyncio>=0.21.0; extra == 'dev'
Requires-Dist: pytest-cov>=4.1.0; extra == 'dev'
Requires-Dist: pytest-timeout>=2.1.0; extra == 'dev'
Requires-Dist: pytest-xdist>=3.3.0; extra == 'dev'
Requires-Dist: pytest>=7.4.0; extra == 'dev'
Requires-Dist: ruff>=0.1.0; extra == 'dev'
Requires-Dist: xlsxwriter>=3.1.0; extra == 'dev'
Provides-Extra: docs
Requires-Dist: mkdocs-git-revision-date-localized-plugin>=1.2.0; extra == 'docs'
Requires-Dist: mkdocs-material>=9.5.0; extra == 'docs'
Requires-Dist: mkdocs>=1.6.0; extra == 'docs'
Requires-Dist: mkdocstrings[python]>=0.24.0; extra == 'docs'
Provides-Extra: oanda
Requires-Dist: oandapyv20>=0.7.0; extra == 'oanda'
Provides-Extra: yahoo
Requires-Dist: yfinance>=0.2.0; extra == 'yahoo'
